{"metaData":[{"name":"Ściana podstawowa:AE_Ogólne - 440 mm:350955","id":"24ZTSdM7bD39hX0jOUfJC3","tag":"350955","objectType":"Ściana podstawowa:AE_Ogólne - 440 mm"},{"name":"Ściana podstawowa:AE_Ogólne - 380mm:607754","id":"1NZWvKXt9C1ANRygIr4qx1","tag":"607754","objectType":"Ściana podstawowa:AE_Ogólne - 380mm"},{"name":"Ściana podstawowa:AE_Ogólne - 440 mm:607757","id":"1NZWvKXt9C1ANRygIr4qx6","tag":"607757","objectType":"Ściana podstawowa:AE_Ogólne - 440 mm"},{"name":"Ściana podstawowa:AE_Ogólne - 440 mm:607760","id":"1NZWvKXt9C1ANRygIr4qxR","tag":"607760","objectType":"Ściana podstawowa:AE_Ogólne - 440 mm"},{"name":"Ściana podstawowa:AE_Ogólne - 120 mm:608532","id":"1NZWvKXt9C1ANRygIr4q7V","tag":"608532","objectType":"Ściana podstawowa:AE_Ogólne - 120 mm"},{"name":"Ściana podstawowa:AE_Ogólne - 120 mm:610527","id":"2eutcpmFbD2fi1tNUuxLT4","tag":"610527","objectType":"Ściana podstawowa:AE_Ogólne - 120 mm"},{"name":"Ściana podstawowa:AE_Ogólne - 120 mm:610622","id":"2eutcpmFbD2fi1tNUuxLQb","tag":"610622","objectType":"Ściana podstawowa:AE_Ogólne - 120 mm"},{"name":"Ściana podstawowa:AE_Ogólne - 120 mm:610835","id":"2eutcpmFbD2fi1tNUuxLM8","tag":"610835","objectType":"Ściana podstawowa:AE_Ogólne - 120 mm"},{"name":"Ściana podstawowa:AE_Ogólne - 120 mm:610972","id":"2eutcpmFbD2fi1tNUuxLK7","tag":"610972","objectType":"Ściana podstawowa:AE_Ogólne - 120 mm"},{"name":"Ściana podstawowa:AE_Ogólne - 440 mm:616651","id":"3Z0_ocZ1v1xgmF9OBVd7fK","tag":"616651","objectType":"Ściana podstawowa:AE_Ogólne - 440 mm"},{"name":"Ściana podstawowa:AE_Ogólne - 440 mm:616745","id":"3Z0_ocZ1v1xgmF9OBVd7ks","tag":"616745","objectType":"Ściana podstawowa:AE_Ogólne - 440 mm"},{"name":"Ściana podstawowa:AE_Ogólne - 440 mm:617089","id":"3Z0_ocZ1v1xgmF9OBVd7WU","tag":"617089","objectType":"Ściana podstawowa:AE_Ogólne - 440 mm"},{"name":"Ściana podstawowa:AE_Ogólne - 440 mm:617150","id":"3Z0_ocZ1v1xgmF9OBVd7WX","tag":"617150","objectType":"Ściana podstawowa:AE_Ogólne - 440 mm"},{"name":"Ściana podstawowa:AE_Ogólne - 120 mm:617779","id":"3Z0_ocZ1v1xgmF9OBVd7_i","tag":"617779","objectType":"Ściana podstawowa:AE_Ogólne - 120 mm"},{"name":"Ściana podstawowa:AE_Ogólne - 120 mm:621125","id":"1A3Dp$23f7QvlxQ4DBDsqc","tag":"621125","objectType":"Ściana podstawowa:AE_Ogólne - 120 mm"},{"name":"Ściana podstawowa:AE_Ogólne - 120 mm:883882","id":"0oVDmqVK92uhvxp1TDjClQ","tag":"883882","objectType":"Ściana podstawowa:AE_Ogólne - 120 mm"},{"name":"Ściana podstawowa:AE_Ogólne - 120 mm:884019","id":"0oVDmqVK92uhvxp1TDjCf3","tag":"884019","objectType":"Ściana podstawowa:AE_Ogólne - 120 mm"},{"name":"Ściana podstawowa:AE_Ogólne - 120 mm:884126","id":"0oVDmqVK92uhvxp1TDjChk","tag":"884126","objectType":"Ściana podstawowa:AE_Ogólne - 120 mm"},{"name":"Ściana podstawowa:AE_Ogólne - 120 mm:884202","id":"0oVDmqVK92uhvxp1TDjCgQ","tag":"884202","objectType":"Ściana podstawowa:AE_Ogólne - 120 mm"},{"name":"Ściana podstawowa:AE_Ogólne - 120 mm:884956","id":"0oVDmqVK92uhvxp1TDj3Ui","tag":"884956","objectType":"Ściana podstawowa:AE_Ogólne - 120 mm"},{"name":"Ściana podstawowa:AE_Ogólne - 440 mm:332598","id":"2itRpYRzvEvf$5LWhLaYJ_","tag":"332598","objectType":"Ściana podstawowa:AE_Ogólne - 440 mm"},{"name":"Ściana podstawowa:AE_Ogólne - 440 mm:333016","id":"2itRpYRzvEvf$5LWhLaYCG","tag":"333016","objectType":"Ściana podstawowa:AE_Ogólne - 440 mm"},{"name":"Ściana podstawowa:AE_Ogólne - 440 mm:334713","id":"26x_QKsKz3xfPtRisL2G8W","tag":"334713","objectType":"Ściana podstawowa:AE_Ogólne - 440 mm"},{"name":"Ściana podstawowa:AE_Ogólne - 440 mm:350253","id":"24ZTSdM7bD39hX0jOUfJ75","tag":"350253","objectType":"Ściana podstawowa:AE_Ogólne - 440 mm"},{"name":"Ściana podstawowa:AE_Ogólne - 380mm:350364","id":"24ZTSdM7bD39hX0jOUfJ5q","tag":"350364","objectType":"Ściana podstawowa:AE_Ogólne - 380mm"},{"name":"Ściana podstawowa:AE_Ogólne - 440 mm:352428","id":"24ZTSdM7bD39hX0jOUfGb4","tag":"352428","objectType":"Ściana podstawowa:AE_Ogólne - 440 mm"},{"name":"Ściana podstawowa:AE_Ogólne - 440 mm:355104","id":"24ZTSdM7bD39hX0jOUfGB8","tag":"355104","objectType":"Ściana podstawowa:AE_Ogólne - 440 mm"},{"name":"Ściana podstawowa:AE_Ogólne - 440 mm:355429","id":"24ZTSdM7bD39hX0jOUfGMD","tag":"355429","objectType":"Ściana podstawowa:AE_Ogólne - 440 mm"},{"name":"Ściana podstawowa:AE_Ogólne - 440 mm:355617","id":"24ZTSdM7bD39hX0jOUfGJ9","tag":"355617","objectType":"Ściana podstawowa:AE_Ogólne - 440 mm"},{"name":"Ściana podstawowa:AE_Ogólne - 300 mm:355841","id":"24ZTSdM7bD39hX0jOUfGVf","tag":"355841","objectType":"Ściana podstawowa:AE_Ogólne - 300 mm"},{"name":"Ściana podstawowa:AE_Ogólne - 120 mm:356500","id":"24ZTSdM7bD39hX0jOUfHby","tag":"356500","objectType":"Ściana podstawowa:AE_Ogólne - 120 mm"},{"name":"Ściana podstawowa:AE_Ogólne - 120 mm:356649","id":"24ZTSdM7bD39hX0jOUfHZ1","tag":"356649","objectType":"Ściana podstawowa:AE_Ogólne - 120 mm"},{"name":"Ściana podstawowa:AE_Ogólne - 120 mm:356919","id":"24ZTSdM7bD39hX0jOUfHlV","tag":"356919","objectType":"Ściana podstawowa:AE_Ogólne - 120 mm"},{"name":"Ściana podstawowa:AE_Ogólne - 240 mm:357446","id":"24ZTSdM7bD39hX0jOUfHsk","tag":"357446","objectType":"Ściana podstawowa:AE_Ogólne - 240 mm"},{"name":"Ściana podstawowa:AE_Ogólne - 240 mm:357794","id":"24ZTSdM7bD39hX0jOUfHnA","tag":"357794","objectType":"Ściana podstawowa:AE_Ogólne - 240 mm"},{"name":"Ściana podstawowa:AE_Ogólne - 240 mm:357948","id":"24ZTSdM7bD39hX0jOUfH$K","tag":"357948","objectType":"Ściana podstawowa:AE_Ogólne - 240 mm"},{"name":"Ściana podstawowa:AE_Ogólne - 500 mm:358236","id":"24ZTSdM7bD39hX0jOUfHwq","tag":"358236","objectType":"Ściana podstawowa:AE_Ogólne - 500 mm"},{"name":"Ściana podstawowa:AE_Ogólne - 500 mm:358697","id":"24ZTSdM7bD39hX0jOUfH31","tag":"358697","objectType":"Ściana podstawowa:AE_Ogólne - 500 mm"},{"name":"Ściana podstawowa:AE_Ogólne - 240 mm:359032","id":"24ZTSdM7bD39hX0jOUfHEG","tag":"359032","objectType":"Ściana podstawowa:AE_Ogólne - 240 mm"},{"name":"Ściana podstawowa:AE_Ogólne - 240 mm:359539","id":"0g8FOw1mX0wREweb2m_401","tag":"359539","objectType":"Ściana podstawowa:AE_Ogólne - 240 mm"},{"name":"Ściana podstawowa:AE_Ogólne - 240 mm:360227","id":"0g8FOw1mX0wREweb2m_4DH","tag":"360227","objectType":"Ściana podstawowa:AE_Ogólne - 240 mm"},{"name":"Ściana podstawowa:AE_Ogólne - 240 mm:360318","id":"0g8FOw1mX0wREweb2m_4CC","tag":"360318","objectType":"Ściana podstawowa:AE_Ogólne - 240 mm"},{"name":"Ściana podstawowa:AE_Ogólne - 240 mm:360387","id":"0g8FOw1mX0wREweb2m_4En","tag":"360387","objectType":"Ściana podstawowa:AE_Ogólne - 240 mm"},{"name":"Ściana podstawowa:AE_Ogólne - 240 mm:360461","id":"0g8FOw1mX0wREweb2m_Bn$","tag":"360461","objectType":"Ściana podstawowa:AE_Ogólne - 240 mm"},{"name":"Ściana podstawowa:AE_Ogólne - 240 mm:360858","id":"0g8FOw1mX0wREweb2m_Bte","tag":"360858","objectType":"Ściana podstawowa:AE_Ogólne - 240 mm"},{"name":"Ściana podstawowa:AE_Ogólne - 240 mm:360982","id":"0g8FOw1mX0wREweb2m_Bva","tag":"360982","objectType":"Ściana podstawowa:AE_Ogólne - 240 mm"},{"name":"Ściana podstawowa:AE_Ogólne - 120 mm:361223","id":"0g8FOw1mX0wREweb2m_Bzr","tag":"361223","objectType":"Ściana podstawowa:AE_Ogólne - 120 mm"},{"name":"Ściana podstawowa:AE_Ogólne - 120 mm:361379","id":"0g8FOw1mX0wREweb2m_B$H","tag":"361379","objectType":"Ściana podstawowa:AE_Ogólne - 120 mm"},{"name":"Ściana podstawowa:AE_Ogólne - 240 mm:362279","id":"0g8FOw1mX0wREweb2m_BjL","tag":"362279","objectType":"Ściana podstawowa:AE_Ogólne - 240 mm"},{"name":"Ściana podstawowa:AE_Ogólne - 120 mm:362416","id":"0g8FOw1mX0wREweb2m_Bl2","tag":"362416","objectType":"Ściana podstawowa:AE_Ogólne - 120 mm"},{"name":"Ściana podstawowa:AE_Ogólne - 120 mm:362698","id":"0g8FOw1mX0wREweb2m_BIu","tag":"362698","objectType":"Ściana podstawowa:AE_Ogólne - 120 mm"},{"name":"Ściana podstawowa:AE_Ogólne - 240 mm:363675","id":"0g8FOw1mX0wREweb2m_B3f","tag":"363675","objectType":"Ściana podstawowa:AE_Ogólne - 240 mm"},{"name":"Ściana podstawowa:AE_Ogólne - 240 mm:363925","id":"0g8FOw1mX0wREweb2m_B7d","tag":"363925","objectType":"Ściana podstawowa:AE_Ogólne - 240 mm"},{"name":"Ściana podstawowa:AE_Ogólne - 240 mm:367465","id":"0g8FOw1mX0wREweb2m_ASR","tag":"367465","objectType":"Ściana podstawowa:AE_Ogólne - 240 mm"},{"name":"Ściana podstawowa:AE_Ogólne - 120 mm:367756","id":"0g8FOw1mX0wREweb2m_A3_","tag":"367756","objectType":"Ściana podstawowa:AE_Ogólne - 120 mm"},{"name":"Ściana podstawowa:AE_Ogólne - 240 mm:367895","id":"0g8FOw1mX0wREweb2m_A5b","tag":"367895","objectType":"Ściana podstawowa:AE_Ogólne - 240 mm"},{"name":"Ściana podstawowa:AE_Ogólne - 120 mm:368158","id":"0g8FOw1mX0wREweb2m_A9i","tag":"368158","objectType":"Ściana podstawowa:AE_Ogólne - 120 mm"},{"name":"Ściana podstawowa:AE_Ogólne - 120 mm:368291","id":"0g8FOw1mX0wREweb2m_ABH","tag":"368291","objectType":"Ściana podstawowa:AE_Ogólne - 120 mm"},{"name":"Ściana podstawowa:AE_Ogólne - 120 mm:368390","id":"0g8FOw1mX0wREweb2m_ADq","tag":"368390","objectType":"Ściana podstawowa:AE_Ogólne - 120 mm"},{"name":"Ściana podstawowa:AE_Ogólne - 240 mm:368757","id":"0g8FOw1mX0wREweb2m_9m7","tag":"368757","objectType":"Ściana podstawowa:AE_Ogólne - 240 mm"},{"name":"Ściana podstawowa:AE_Ogólne - 240 mm:368842","id":"0g8FOw1mX0wREweb2m_9ou","tag":"368842","objectType":"Ściana podstawowa:AE_Ogólne - 240 mm"},{"name":"Ściana podstawowa:AE_Ogólne - 120 mm:369002","id":"0g8FOw1mX0wREweb2m_9qO","tag":"369002","objectType":"Ściana podstawowa:AE_Ogólne - 120 mm"},{"name":"Ściana podstawowa:AE_Ogólne - 300 mm:383513","id":"10hjMMF_z1qPCktVCENyE$","tag":"383513","objectType":"Ściana podstawowa:AE_Ogólne - 300 mm"},{"name":"Ściana podstawowa:AE_Ogólne - 300 mm:383795","id":"10hjMMF_z1qPCktVCENyAL","tag":"383795","objectType":"Ściana podstawowa:AE_Ogólne - 300 mm"},{"name":"Ściana podstawowa:AE_Ogólne - 380mm:384117","id":"10hjMMF_z1qPCktVCENyNJ","tag":"384117","objectType":"Ściana podstawowa:AE_Ogólne - 380mm"},{"name":"Ściana podstawowa:AE_Ogólne - 300 mm:384336","id":"10hjMMF_z1qPCktVCENyJs","tag":"384336","objectType":"Ściana podstawowa:AE_Ogólne - 300 mm"},{"name":"Ściana podstawowa:AE_Ogólne - 440 mm:384844","id":"10hjMMF_z1qPCktVCENyRg","tag":"384844","objectType":"Ściana podstawowa:AE_Ogólne - 440 mm"},{"name":"Ściana podstawowa:AE_Ogólne - 440 mm:405690","id":"0kXaNh7avF7QHy3tLqkU$E","tag":"405690","objectType":"Ściana podstawowa:AE_Ogólne - 440 mm"},{"name":"Ściana podstawowa:AE_Witryna - 50 mm:419265","id":"1CF3HP6Tb4QuEgKCXITYiH","tag":"419265","objectType":"Ściana podstawowa:AE_Witryna - 50 mm"},{"name":"Ściana podstawowa:AE_Ogólne - 440 mm:419339","id":"1CF3HP6Tb4QuEgKCXITYZR","tag":"419339","objectType":"Ściana podstawowa:AE_Ogólne - 440 mm"},{"name":"Ściana podstawowa:AE_Ogólne - 500 mm:420272","id":"1CF3HP6Tb4QuEgKCXITYTW","tag":"420272","objectType":"Ściana podstawowa:AE_Ogólne - 500 mm"},{"name":"Ściana podstawowa:AE_Ogólne - 500 mm:420353","id":"1CF3HP6Tb4QuEgKCXITYJH","tag":"420353","objectType":"Ściana podstawowa:AE_Ogólne - 500 mm"},{"name":"Ściana podstawowa:AE_Witryna - 50 mm:420705","id":"1CF3HP6Tb4QuEgKCXITYMn","tag":"420705","objectType":"Ściana podstawowa:AE_Witryna - 50 mm"},{"name":"Ściana podstawowa:AE_Ogólne - 440 mm:540124","id":"3EJD64y2T4EvIIlRMTC4OZ","tag":"540124","objectType":"Ściana podstawowa:AE_Ogólne - 440 mm"},{"name":"Ściana podstawowa:AE_Ogólne - 440 mm:540807","id":"3EJD64y2T4EvIIlRMTC3ju","tag":"540807","objectType":"Ściana podstawowa:AE_Ogólne - 440 mm"},{"name":"Ściana podstawowa:AE_Ogólne - 440 mm:541027","id":"3EJD64y2T4EvIIlRMTC3gS","tag":"541027","objectType":"Ściana podstawowa:AE_Ogólne - 440 mm"},{"name":"Ściana podstawowa:AE_Ogólne - 240 mm:541591","id":"3EJD64y2T4EvIIlRMTC3Xe","tag":"541591","objectType":"Ściana podstawowa:AE_Ogólne - 240 mm"},{"name":"Ściana podstawowa:AE_Ogólne - 240 mm:541764","id":"3EJD64y2T4EvIIlRMTC3_x","tag":"541764","objectType":"Ściana podstawowa:AE_Ogólne - 240 mm"},{"name":"Ściana podstawowa:AE_Ogólne - 240 mm:541847","id":"3EJD64y2T4EvIIlRMTC3ze","tag":"541847","objectType":"Ściana podstawowa:AE_Ogólne - 240 mm"},{"name":"Ściana podstawowa:AE_Ogólne - 240 mm:541969","id":"3EJD64y2T4EvIIlRMTC3xk","tag":"541969","objectType":"Ściana podstawowa:AE_Ogólne - 240 mm"},{"name":"Ściana podstawowa:AE_Ogólne - 240 mm:542041","id":"3EJD64y2T4EvIIlRMTC3wc","tag":"542041","objectType":"Ściana podstawowa:AE_Ogólne - 240 mm"},{"name":"Ściana podstawowa:AE_Ogólne - 240 mm:542079","id":"3EJD64y2T4EvIIlRMTC3w0","tag":"542079","objectType":"Ściana podstawowa:AE_Ogólne - 240 mm"},{"name":"Ściana podstawowa:AE_Ogólne - 440 mm:542149","id":"3EJD64y2T4EvIIlRMTC3uw","tag":"542149","objectType":"Ściana podstawowa:AE_Ogólne - 440 mm"},{"name":"Ściana podstawowa:AE_Ogólne - 240 mm:542450","id":"3EJD64y2T4EvIIlRMTC3qD","tag":"542450","objectType":"Ściana podstawowa:AE_Ogólne - 240 mm"},{"name":"Ściana podstawowa:AE_Ogólne - 120 mm:542651","id":"3EJD64y2T4EvIIlRMTC3n4","tag":"542651","objectType":"Ściana podstawowa:AE_Ogólne - 120 mm"},{"name":"Ściana podstawowa:AE_Ogólne - 120 mm:543192","id":"3EJD64y2T4EvIIlRMTC38d","tag":"543192","objectType":"Ściana podstawowa:AE_Ogólne - 120 mm"},{"name":"Ściana podstawowa:AE_Ogólne - 120 mm:545499","id":"3EJD64y2T4EvIIlRMTC2aa","tag":"545499","objectType":"Ściana podstawowa:AE_Ogólne - 120 mm"},{"name":"Ściana podstawowa:AE_Ogólne - 380mm:550875","id":"15jBgJ4df0GwXJuL1YgfTg","tag":"550875","objectType":"Ściana podstawowa:AE_Ogólne - 380mm"},{"name":"Ściana podstawowa:AE_Ogólne - 120 mm:552458","id":"15jBgJ4df0GwXJuL1Ygfwx","tag":"552458","objectType":"Ściana podstawowa:AE_Ogólne - 120 mm"},{"name":"Ściana podstawowa:AE_Ogólne - 380mm:553074","id":"15jBgJ4df0GwXJuL1Yge33","tag":"553074","objectType":"Ściana podstawowa:AE_Ogólne - 380mm"},{"name":"Ściana podstawowa:AE_Ogólne - 440 mm:553524","id":"15jBgJ4df0GwXJuL1YgeA5","tag":"553524","objectType":"Ściana podstawowa:AE_Ogólne - 440 mm"},{"name":"Ściana podstawowa:AE_Ogólne - 440 mm:554952","id":"2KPufnVTv81gAAH7LH46pU","tag":"554952","objectType":"Ściana podstawowa:AE_Ogólne - 440 mm"},{"name":"Ściana podstawowa:AE_Ogólne - 440 mm:555449","id":"2KPufnVTv81gAAH7LH46Al","tag":"555449","objectType":"Ściana podstawowa:AE_Ogólne - 440 mm"},{"name":"Ściana podstawowa:AE_Ogólne - 380mm:592835","id":"1tDexFO5P1iPWqmzYGFQ_k","tag":"592835","objectType":"Ściana podstawowa:AE_Ogólne - 380mm"},{"name":"Ściana podstawowa:AE_Ogólne - kotara:593698","id":"1tDexFO5P1iPWqmzYGFQjF","tag":"593698","objectType":"Ściana podstawowa:AE_Ogólne - kotara"},{"name":"Ściana podstawowa:AE_Ogólne - kotara:594542","id":"1tDexFO5P1iPWqmzYGFRO3","tag":"594542","objectType":"Ściana podstawowa:AE_Ogólne - kotara"},{"name":"Ściana podstawowa:AE_Ogólne - 120 mm:598301","id":"2uUynbq0f9RBW7aowMJs4Z","tag":"598301","objectType":"Ściana podstawowa:AE_Ogólne - 120 mm"},{"name":"Ściana podstawowa:AE_Ogólne - 440 mm:600427","id":"2uUynbq0f9RBW7aowMJsbL","tag":"600427","objectType":"Ściana podstawowa:AE_Ogólne - 440 mm"},{"name":"Ściana podstawowa:AE_Ogólne - 440 mm:627490","id":"1v_sWJlo59X8lj20i1p7dz","tag":"627490","objectType":"Ściana podstawowa:AE_Ogólne - 440 mm"},{"name":"Ściana podstawowa:AE_Ogólne - 120 mm:840999","id":"0mKwvPVC9DkO5ql64APhHg","tag":"840999","objectType":"Ściana podstawowa:AE_Ogólne - 120 mm"},{"name":"Ściana podstawowa:AE_Ogólne - 120 mm:352729","id":"24ZTSdM7bD39hX0jOUfGWn","tag":"352729","objectType":"Ściana podstawowa:AE_Ogólne - 120 mm"},{"name":"Ściana podstawowa:AE_Ogólne - 120 mm:352867","id":"24ZTSdM7bD39hX0jOUfGkB","tag":"352867","objectType":"Ściana podstawowa:AE_Ogólne - 120 mm"},{"name":"Ściana podstawowa:AE_Ogólne - 120 mm:352933","id":"24ZTSdM7bD39hX0jOUfGjD","tag":"352933","objectType":"Ściana podstawowa:AE_Ogólne - 120 mm"},{"name":"Ściana podstawowa:AE_Ogólne - 240 mm:359156","id":"24ZTSdM7bD39hX0jOUfHCS","tag":"359156","objectType":"Ściana podstawowa:AE_Ogólne - 240 mm"},{"name":"Ściana podstawowa:AE_Ogólne - 120 mm:359224","id":"24ZTSdM7bD39hX0jOUfHBG","tag":"359224","objectType":"Ściana podstawowa:AE_Ogólne - 120 mm"},{"name":"Ściana podstawowa:AE_Ogólne - 120 mm:359902","id":"0g8FOw1mX0wREweb2m_46i","tag":"359902","objectType":"Ściana podstawowa:AE_Ogólne - 120 mm"},{"name":"Ściana podstawowa:AE_Ogólne - 120 mm:360024","id":"0g8FOw1mX0wREweb2m_48g","tag":"360024","objectType":"Ściana podstawowa:AE_Ogólne - 120 mm"},{"name":"Ściana podstawowa:AE_Ogólne - 240 mm:391846","id":"0kXaNh7avF7QHy3tLqkYNI","tag":"391846","objectType":"Ściana podstawowa:AE_Ogólne - 240 mm"},{"name":"Ściana podstawowa:AE_Ogólne - 440 mm:412054","id":"2PsTDU3rPC3Q4jVZxaRhcC","tag":"412054","objectType":"Ściana podstawowa:AE_Ogólne - 440 mm"},{"name":"Ściana podstawowa:AE_Ogólne - 440 mm:421220","id":"2S5Uyqz1PAvOb6Q$kxXyJU","tag":"421220","objectType":"Ściana podstawowa:AE_Ogólne - 440 mm"},{"name":"Ściana podstawowa:AE_Ogólne - 240 mm:422582","id":"2S5Uyqz1PAvOb6Q$kxXziC","tag":"422582","objectType":"Ściana podstawowa:AE_Ogólne - 240 mm"},{"name":"Ściana podstawowa:AE_Ogólne - 240 mm:422920","id":"2S5Uyqz1PAvOb6Q$kxXzso","tag":"422920","objectType":"Ściana podstawowa:AE_Ogólne - 240 mm"},{"name":"Ściana podstawowa:AE_Ogólne - 120 mm:422985","id":"2S5Uyqz1PAvOb6Q$kxXztp","tag":"422985","objectType":"Ściana podstawowa:AE_Ogólne - 120 mm"},{"name":"Ściana podstawowa:AE_Ogólne - 380mm:422989","id":"2S5Uyqz1PAvOb6Q$kxXztt","tag":"422989","objectType":"Ściana podstawowa:AE_Ogólne - 380mm"},{"name":"Ściana podstawowa:AE_Ogólne - 300 mm:422990","id":"2S5Uyqz1PAvOb6Q$kxXztq","tag":"422990","objectType":"Ściana podstawowa:AE_Ogólne - 300 mm"},{"name":"Ściana podstawowa:AE_Ogólne - 500 mm:422991","id":"2S5Uyqz1PAvOb6Q$kxXztr","tag":"422991","objectType":"Ściana podstawowa:AE_Ogólne - 500 mm"},{"name":"Ściana podstawowa:AE_Ogólne - 380mm:423278","id":"2S5Uyqz1PAvOb6Q$kxXzpK","tag":"423278","objectType":"Ściana podstawowa:AE_Ogólne - 380mm"},{"name":"Ściana podstawowa:AE_Ogólne - 380mm:423578","id":"2S5Uyqz1PAvOb6Q$kxXzyW","tag":"423578","objectType":"Ściana podstawowa:AE_Ogólne - 380mm"},{"name":"Ściana podstawowa:AE_Ogólne - 120 mm:423999","id":"2S5Uyqz1PAvOb6Q$kxXz65","tag":"423999","objectType":"Ściana podstawowa:AE_Ogólne - 120 mm"},{"name":"Ściana podstawowa:AE_Ogólne - 120 mm:424096","id":"2S5Uyqz1PAvOb6Q$kxXz4Q","tag":"424096","objectType":"Ściana podstawowa:AE_Ogólne - 120 mm"},{"name":"Ściana podstawowa:AE_Ogólne - 120 mm:424278","id":"2S5Uyqz1PAvOb6Q$kxXz3i","tag":"424278","objectType":"Ściana podstawowa:AE_Ogólne - 120 mm"},{"name":"Ściana podstawowa:AE_Ogólne - 120 mm:424604","id":"2S5Uyqz1PAvOb6Q$kxXzCc","tag":"424604","objectType":"Ściana podstawowa:AE_Ogólne - 120 mm"},{"name":"Ściana podstawowa:AE_Ogólne - 120 mm:424719","id":"2S5Uyqz1PAvOb6Q$kxXzAr","tag":"424719","objectType":"Ściana podstawowa:AE_Ogólne - 120 mm"},{"name":"Ściana podstawowa:AE_Ogólne - 120 mm:424891","id":"2S5Uyqz1PAvOb6Q$kxXz81","tag":"424891","objectType":"Ściana podstawowa:AE_Ogólne - 120 mm"},{"name":"Ściana podstawowa:AE_Ogólne - 300 mm:425113","id":"2S5Uyqz1PAvOb6Q$kxXzKZ","tag":"425113","objectType":"Ściana podstawowa:AE_Ogólne - 300 mm"},{"name":"Ściana podstawowa:AE_Ogólne - 240 mm:426002","id":"2S5Uyqz1PAvOb6Q$kxXoce","tag":"426002","objectType":"Ściana podstawowa:AE_Ogólne - 240 mm"},{"name":"Ściana podstawowa:AE_Ogólne - 240 mm:426136","id":"2S5Uyqz1PAvOb6Q$kxXoaY","tag":"426136","objectType":"Ściana podstawowa:AE_Ogólne - 240 mm"},{"name":"Ściana podstawowa:AE_Ogólne - 240 mm:426220","id":"2S5Uyqz1PAvOb6Q$kxXobM","tag":"426220","objectType":"Ściana podstawowa:AE_Ogólne - 240 mm"},{"name":"Ściana podstawowa:AE_Ogólne - 240 mm:426329","id":"2S5Uyqz1PAvOb6Q$kxXoZZ","tag":"426329","objectType":"Ściana podstawowa:AE_Ogólne - 240 mm"},{"name":"Ściana podstawowa:AE_Ogólne - 240 mm:426475","id":"2S5Uyqz1PAvOb6Q$kxXoXH","tag":"426475","objectType":"Ściana podstawowa:AE_Ogólne - 240 mm"},{"name":"Ściana podstawowa:AE_Ogólne - 240 mm:426659","id":"2S5Uyqz1PAvOb6Q$kxXoiP","tag":"426659","objectType":"Ściana podstawowa:AE_Ogólne - 240 mm"},{"name":"Ściana podstawowa:AE_Ogólne - 120 mm:426848","id":"2S5Uyqz1PAvOb6Q$kxXohQ","tag":"426848","objectType":"Ściana podstawowa:AE_Ogólne - 120 mm"},{"name":"Ściana podstawowa:AE_Ogólne - 120 mm:427080","id":"2S5Uyqz1PAvOb6Q$kxXoto","tag":"427080","objectType":"Ściana podstawowa:AE_Ogólne - 120 mm"},{"name":"Ściana podstawowa:AE_Ogólne - 120 mm:427151","id":"2S5Uyqz1PAvOb6Q$kxXoqr","tag":"427151","objectType":"Ściana podstawowa:AE_Ogólne - 120 mm"},{"name":"Ściana podstawowa:AE_Ogólne - 380mm:428788","id":"2S5Uyqz1PAvOb6Q$kxXoDE","tag":"428788","objectType":"Ściana podstawowa:AE_Ogólne - 380mm"},{"name":"Ściana podstawowa:AE_Ogólne - 440 mm:428913","id":"2S5Uyqz1PAvOb6Q$kxXoBB","tag":"428913","objectType":"Ściana podstawowa:AE_Ogólne - 440 mm"},{"name":"Ściana podstawowa:AE_Ogólne - 380mm:429113","id":"2S5Uyqz1PAvOb6Q$kxXoM3","tag":"429113","objectType":"Ściana podstawowa:AE_Ogólne - 380mm"},{"name":"Ściana podstawowa:AE_Ogólne - 440 mm:429343","id":"2S5Uyqz1PAvOb6Q$kxXoIb","tag":"429343","objectType":"Ściana podstawowa:AE_Ogólne - 440 mm"},{"name":"Ściana podstawowa:AE_Ogólne - 120 mm:431351","id":"2S5Uyqz1PAvOb6Q$kxXprD","tag":"431351","objectType":"Ściana podstawowa:AE_Ogólne - 120 mm"},{"name":"Ściana podstawowa:AE_Ogólne - 120 mm:431513","id":"2S5Uyqz1PAvOb6Q$kxXpmZ","tag":"431513","objectType":"Ściana podstawowa:AE_Ogólne - 120 mm"},{"name":"Ściana podstawowa:AE_Ogólne - 120 mm:431548","id":"2S5Uyqz1PAvOb6Q$kxXpm6","tag":"431548","objectType":"Ściana podstawowa:AE_Ogólne - 120 mm"},{"name":"Ściana podstawowa:AE_Ogólne - 120 mm:431732","id":"2S5Uyqz1PAvOb6Q$kxXp$E","tag":"431732","objectType":"Ściana podstawowa:AE_Ogólne - 120 mm"},{"name":"Ściana podstawowa:AE_Ogólne - 120 mm:431807","id":"2S5Uyqz1PAvOb6Q$kxXpy5","tag":"431807","objectType":"Ściana podstawowa:AE_Ogólne - 120 mm"},{"name":"Ściana podstawowa:AE_Ogólne - 440 mm:432033","id":"2S5Uyqz1PAvOb6Q$kxXpuR","tag":"432033","objectType":"Ściana podstawowa:AE_Ogólne - 440 mm"},{"name":"Ściana podstawowa:AE_Ogólne - 240 mm:432350","id":"2S5Uyqz1PAvOb6Q$kxXp5a","tag":"432350","objectType":"Ściana podstawowa:AE_Ogólne - 240 mm"},{"name":"Ściana podstawowa:AE_Ogólne - 240 mm:432503","id":"2S5Uyqz1PAvOb6Q$kxXp3D","tag":"432503","objectType":"Ściana podstawowa:AE_Ogólne - 240 mm"},{"name":"Ściana podstawowa:AE_Ogólne - 240 mm:432625","id":"2S5Uyqz1PAvOb6Q$kxXp1B","tag":"432625","objectType":"Ściana podstawowa:AE_Ogólne - 240 mm"},{"name":"Ściana podstawowa:AE_Ogólne - 240 mm:432750","id":"2S5Uyqz1PAvOb6Q$kxXpFK","tag":"432750","objectType":"Ściana podstawowa:AE_Ogólne - 240 mm"},{"name":"Ściana podstawowa:AE_Ogólne - 120 mm:432903","id":"2S5Uyqz1PAvOb6Q$kxXpAz","tag":"432903","objectType":"Ściana podstawowa:AE_Ogólne - 120 mm"},{"name":"Ściana podstawowa:AE_Ogólne - 120 mm:433129","id":"2S5Uyqz1PAvOb6Q$kxXp9J","tag":"433129","objectType":"Ściana podstawowa:AE_Ogólne - 120 mm"},{"name":"Ściana podstawowa:AE_Ogólne - 380mm:433253","id":"2S5Uyqz1PAvOb6Q$kxXpNV","tag":"433253","objectType":"Ściana podstawowa:AE_Ogólne - 380mm"},{"name":"Ściana podstawowa:AE_Ogólne - 300 mm:433254","id":"2S5Uyqz1PAvOb6Q$kxXpNS","tag":"433254","objectType":"Ściana podstawowa:AE_Ogólne - 300 mm"},{"name":"Ściana podstawowa:AE_Ogólne - 500 mm:433255","id":"2S5Uyqz1PAvOb6Q$kxXpNT","tag":"433255","objectType":"Ściana podstawowa:AE_Ogólne - 500 mm"},{"name":"Ściana podstawowa:AE_Ogólne - 380mm:433256","id":"2S5Uyqz1PAvOb6Q$kxXpNI","tag":"433256","objectType":"Ściana podstawowa:AE_Ogólne - 380mm"},{"name":"Ściana podstawowa:AE_Ogólne - 380mm:433257","id":"2S5Uyqz1PAvOb6Q$kxXpNJ","tag":"433257","objectType":"Ściana podstawowa:AE_Ogólne - 380mm"},{"name":"Ściana podstawowa:AE_Ogólne - 240 mm:433835","id":"0TW4fkUWTCieKBGUi_3$Hx","tag":"433835","objectType":"Ściana podstawowa:AE_Ogólne - 240 mm"},{"name":"Ściana podstawowa:AE_Ogólne - 240 mm:433999","id":"0TW4fkUWTCieKBGUi_3$MV","tag":"433999","objectType":"Ściana podstawowa:AE_Ogólne - 240 mm"},{"name":"Ściana podstawowa:AE_Ogólne - 240 mm:434118","id":"0TW4fkUWTCieKBGUi_3$KM","tag":"434118","objectType":"Ściana podstawowa:AE_Ogólne - 240 mm"},{"name":"Ściana podstawowa:AE_Ogólne - 240 mm:434190","id":"0TW4fkUWTCieKBGUi_3yhU","tag":"434190","objectType":"Ściana podstawowa:AE_Ogólne - 240 mm"},{"name":"Ściana podstawowa:AE_Ogólne - 120 mm:434355","id":"0TW4fkUWTCieKBGUi_3yfZ","tag":"434355","objectType":"Ściana podstawowa:AE_Ogólne - 120 mm"},{"name":"Ściana podstawowa:AE_Ogólne - 120 mm:434585","id":"0TW4fkUWTCieKBGUi_3yj9","tag":"434585","objectType":"Ściana podstawowa:AE_Ogólne - 120 mm"},{"name":"Ściana podstawowa:AE_Ogólne - 120 mm:435413","id":"0TW4fkUWTCieKBGUi_3yu5","tag":"435413","objectType":"Ściana podstawowa:AE_Ogólne - 120 mm"},{"name":"Ściana podstawowa:AE_Ogólne - 120 mm:435486","id":"0TW4fkUWTCieKBGUi_3y$E","tag":"435486","objectType":"Ściana podstawowa:AE_Ogólne - 120 mm"},{"name":"Ściana podstawowa:AE_Ogólne - 120 mm:435679","id":"0TW4fkUWTCieKBGUi_3yyF","tag":"435679","objectType":"Ściana podstawowa:AE_Ogólne - 120 mm"},{"name":"Ściana podstawowa:AE_Ogólne - 120 mm:435914","id":"0TW4fkUWTCieKBGUi_3ymQ","tag":"435914","objectType":"Ściana podstawowa:AE_Ogólne - 120 mm"},{"name":"Ściana podstawowa:AE_Ogólne - 120 mm:436955","id":"0TW4fkUWTCieKBGUi_3y0B","tag":"436955","objectType":"Ściana podstawowa:AE_Ogólne - 120 mm"},{"name":"Ściana podstawowa:AE_Ogólne - 120 mm:437032","id":"0TW4fkUWTCieKBGUi_3y7u","tag":"437032","objectType":"Ściana podstawowa:AE_Ogólne - 120 mm"}]}